<?xml version="1.0" encoding="utf-8" ?>
<dwsync>
<file name="01.jpg" server="cp23.g-dns.com/no83/" local="132276696516498131" remote="132276712200000000" />
<file name="02.jpg" server="cp23.g-dns.com/no83/" local="132276700555479140" remote="132276712200000000" />
<file name="03.jpg" server="cp23.g-dns.com/no83/" local="132276705079151557" remote="132276712200000000" />
<file name="04.jpg" server="cp23.g-dns.com/no83/" local="132276707773048511" remote="132276712200000000" />
<file name="05.jpg" server="cp23.g-dns.com/no83/" local="132276938166971944" remote="132276938400000000" />
<file name="06.jpg" server="cp23.g-dns.com/no83/" local="132276941885651459" remote="132276980400000000" />
<file name="07.jpg" server="cp23.g-dns.com/no83/" local="132276796383500200" remote="132276807600000000" />
<file name="08.jpg" server="cp23.g-dns.com/no83/" local="132276978104206174" remote="132276980400000000" />
<file name="09.jpg" server="cp23.g-dns.com/no83/" local="132276878252459102" remote="132276897600000000" />
<file name="10.jpg" server="cp23.g-dns.com/no83/" local="132276979226901496" remote="132276980400000000" />
<file name="11.jpg" server="cp23.g-dns.com/no83/" local="132276981902197345" remote="132276981600000000" />
<file name="12.jpg" server="cp23.g-dns.com/no83/" local="132276906661127163" remote="132276907200000000" />
</dwsync>