<?xml version="1.0" encoding="utf-8" ?>
<dwsync>
<file name="75-2-2-1.jpg" server="192.168.1.5/compal/no57/" local="130602369317159966" remote="130602528450000000" />
<file name="75-2-2-2.jpg" server="192.168.1.5/compal/no57/" local="130602369772375334" remote="130602528450000000" />
<file name="75-2-2-3.jpg" server="192.168.1.5/compal/no57/" local="130602370276008069" remote="130602528450000000" />
<file name="75-2-2-4.jpg" server="192.168.1.5/compal/no57/" local="130602370531024486" remote="130602528450000000" />
<file name="75-2-2-5.jpg" server="192.168.1.5/compal/no57/" local="130602370774890732" remote="130602528450000000" />
<file name="75-2-2-6.jpg" server="192.168.1.5/compal/no57/" local="130602371299133785" remote="130602528450000000" />
<file name="75-2-2-1.jpg" server="192.168.1.5/compal/no58/" local="130700754086525950" remote="130700757000000000" />
<file name="75-2-2-2.jpg" server="192.168.1.5/compal/no58/" local="130700754231265674" remote="130700757000000000" />
<file name="75-2-2-3.jpg" server="192.168.1.5/compal/no58/" local="130700754377880438" remote="130700757000000000" />
<file name="75-2-2-4.jpg" server="192.168.1.5/compal/no58/" local="130700754542157961" remote="130700757000000000" />
<file name="75-2-2-5.jpg" server="192.168.1.5/compal/no58/" local="130700754752698708" remote="130700757000000000" />
<file name="75-2-2-6.jpg" server="192.168.1.5/compal/no58/" local="130700754918588756" remote="130700757000000000" />
<file name="75-2-2-1.jpg" server="192.168.1.5/compal/no59/" local="130757880282443339" remote="130757973600000000" />
<file name="75-2-2-2.jpg" server="192.168.1.5/compal/no59/" local="130757880116445765" remote="130757973600000000" />
<file name="75-2-2-3.jpg" server="192.168.1.5/compal/no59/" local="130757879974341070" remote="130757973600000000" />
<file name="75-2-2-4.jpg" server="192.168.1.5/compal/no59/" local="130757879819758672" remote="130757973600000000" />
<file name="75-2-2-5.jpg" server="192.168.1.5/compal/no59/" local="130757879672143892" remote="130757973600000000" />
<file name="75-2-2-6.jpg" server="192.168.1.5/compal/no59/" local="130757879470508271" remote="130757973600000000" />
<file name="75-2-2-1.jpg" server="192.168.1.5/compal/no61/" local="130857187381472963" remote="130857246600000000" />
<file name="75-2-2-2.jpg" server="192.168.1.5/compal/no61/" local="130857187524207696" remote="130857246600000000" />
<file name="75-2-2-3.jpg" server="192.168.1.5/compal/no61/" local="130857187685095201" remote="130857246600000000" />
<file name="75-2-2-4.jpg" server="192.168.1.5/compal/no61/" local="130857187968472119" remote="130857246600000000" />
<file name="75-2-2-5.jpg" server="192.168.1.5/compal/no61/" local="130857188272706862" remote="130857246600000000" />
<file name="75-2-2-6.jpg" server="192.168.1.5/compal/no61/" local="130857188472272482" remote="130857246600000000" />
<file name="75-2-2-1.jpg" server="192.168.1.5/compal/no62/" local="130912677628679060" remote="130912732800000000" />
<file name="75-2-2-2.jpg" server="192.168.1.5/compal/no62/" local="130912678564955293" remote="130912732800000000" />
<file name="75-2-2-3.jpg" server="192.168.1.5/compal/no62/" local="130912679112866442" remote="130912732800000000" />
<file name="75-2-2-4.jpg" server="192.168.1.5/compal/no62/" local="130912679258927007" remote="130912732800000000" />
<file name="75-2-2-5.jpg" server="192.168.1.5/compal/no62/" local="130912679443377677" remote="130912732800000000" />
<file name="75-2-2-6.jpg" server="192.168.1.5/compal/no62/" local="130912679599528256" remote="130912732800000000" />
<file name="75-2-2-1.jpg" server="192.168.1.5/compal/no63/" local="131018068235392497" remote="131018131800000000" />
<file name="75-2-2-2.jpg" server="192.168.1.5/compal/no63/" local="131018070255243206" remote="131018131800000000" />
<file name="75-2-2-3.jpg" server="192.168.1.5/compal/no63/" local="131018074177821602" remote="131018131800000000" />
<file name="75-2-2-4.jpg" server="192.168.1.5/compal/no63/" local="131018073439849926" remote="131018131800000000" />
<file name="75-2-2-5.jpg" server="192.168.1.5/compal/no63/" local="131018074352233768" remote="131018131800000000" />
<file name="75-2-2-6.jpg" server="192.168.1.5/compal/no63/" local="131018074507685281" remote="131018131800000000" />
<file name="75-2-2-1.jpg" server="43.254.16.148/no64/" local="131069692183269733" remote="131069694000000000" />
<file name="75-2-2-2.jpg" server="43.254.16.148/no64/" local="131069692324812286" remote="131069694000000000" />
<file name="75-2-2-3.jpg" server="43.254.16.148/no64/" local="131069692499056250" remote="131069694000000000" />
<file name="75-2-2-4.jpg" server="43.254.16.148/no64/" local="131069692657306667" remote="131069694000000000" />
<file name="75-2-2-5.jpg" server="43.254.16.148/no64/" local="131069692826492249" remote="131069694000000000" />
<file name="75-2-2-6.jpg" server="43.254.16.148/no64/" local="131069692989250288" remote="131069694000000000" />
<file name="75-2-2-1.jpg" server="43.254.16.148/no65/" local="131120703524620189" remote="131120857800000000" />
<file name="75-2-2-2.jpg" server="43.254.16.148/no65/" local="131120703839082679" remote="131120857800000000" />
<file name="75-2-2-3.jpg" server="43.254.16.148/no65/" local="131120704779812574" remote="131120857800000000" />
<file name="75-2-2-4.jpg" server="43.254.16.148/no65/" local="131120705536289592" remote="131120857800000000" />
<file name="75-2-2-5.jpg" server="43.254.16.148/no65/" local="131120705836169351" remote="131120857800000000" />
<file name="75-2-2-6.jpg" server="43.254.16.148/no65/" local="131120706230805619" remote="131120857800000000" />
<file name="75-2-2-1.jpg" server="43.254.16.148/no66/" local="131172624838727993" remote="131172729000000000" />
<file name="75-2-2-2.jpg" server="43.254.16.148/no66/" local="131172624688240589" remote="131172729000000000" />
<file name="75-2-2-3.jpg" server="43.254.16.148/no66/" local="131172624559761066" remote="131172729000000000" />
<file name="75-2-2-4.jpg" server="43.254.16.148/no66/" local="131172624442039207" remote="131172729000000000" />
<file name="75-2-2-5.jpg" server="43.254.16.148/no66/" local="131172624273869045" remote="131172729000000000" />
<file name="75-2-2-6.jpg" server="43.254.16.148/no66/" local="131172624163997319" remote="131172729600000000" />
<file name="75-2-2-1.jpg" server="43.254.16.148/no67/" local="131230473023720608" remote="131230511400000000" />
<file name="75-2-2-2.jpg" server="43.254.16.148/no67/" local="131230473185378101" remote="131230511400000000" />
<file name="75-2-2-3.jpg" server="43.254.16.148/no67/" local="131230473380016104" remote="131230511400000000" />
<file name="75-2-2-4.jpg" server="43.254.16.148/no67/" local="131230473685505840" remote="131230511400000000" />
<file name="75-2-2-5.jpg" server="43.254.16.148/no67/" local="131230473906379255" remote="131230511400000000" />
<file name="75-2-2-6.jpg" server="43.254.16.148/no67/" local="131230474127817692" remote="131230511400000000" />
<file name="75-2-2-1.jpg" server="cp23.g-dns.com/no67/" local="131230473023720608" remote="131239066800000000" />
<file name="75-2-2-2.jpg" server="cp23.g-dns.com/no67/" local="131230473185378101" remote="131239066800000000" />
<file name="75-2-2-3.jpg" server="cp23.g-dns.com/no67/" local="131230473380016104" remote="131239066800000000" />
<file name="75-2-2-4.jpg" server="cp23.g-dns.com/no67/" local="131230473685505840" remote="131239066800000000" />
<file name="75-2-2-5.jpg" server="cp23.g-dns.com/no67/" local="131230473906379255" remote="131239066800000000" />
<file name="75-2-2-6.jpg" server="cp23.g-dns.com/no67/" local="131230474127817692" remote="131239066800000000" />
<file name="75-2-2-1.jpg" server="cp23.g-dns.com/no68/" local="131339501012651271" remote="131341018200000000" />
<file name="75-2-2-2.jpg" server="cp23.g-dns.com/no68/" local="131339501156933499" remote="131341018200000000" />
<file name="75-2-2-3.jpg" server="cp23.g-dns.com/no68/" local="131339501408802390" remote="131341018200000000" />
<file name="75-2-2-4.jpg" server="cp23.g-dns.com/no68/" local="131339501610380486" remote="131341018200000000" />
<file name="75-2-2-5.jpg" server="cp23.g-dns.com/no68/" local="131339501788023237" remote="131341018200000000" />
<file name="75-2-2-6.jpg" server="cp23.g-dns.com/no68/" local="131339501960588388" remote="131341018200000000" />
<file name="75-2-2-1.jpg" server="cp23.g-dns.com/no69/" local="131387863753063139" remote="131387894400000000" />
<file name="75-2-2-2.jpg" server="cp23.g-dns.com/no69/" local="131387863895678384" remote="131387894400000000" />
<file name="75-2-2-3.jpg" server="cp23.g-dns.com/no69/" local="131387864034102481" remote="131387894400000000" />
<file name="75-2-2-4.jpg" server="cp23.g-dns.com/no69/" local="131387864170817086" remote="131387894400000000" />
<file name="75-2-2-5.jpg" server="cp23.g-dns.com/no69/" local="131387864297211599" remote="131387894400000000" />
<file name="75-2-2-6.jpg" server="cp23.g-dns.com/no69/" local="131387864417399942" remote="131387894400000000" />
<file name="75-2-2-1.jpg" server="cp23.g-dns.com/no70/" local="131438853562082820" remote="131441261400000000" />
<file name="75-2-2-2.jpg" server="cp23.g-dns.com/no70/" local="131438853437537005" remote="131441261400000000" />
<file name="75-2-2-3.jpg" server="cp23.g-dns.com/no70/" local="131438853319497016" remote="131441261400000000" />
<file name="75-2-2-4.jpg" server="cp23.g-dns.com/no70/" local="131438853176223822" remote="131441261400000000" />
<file name="75-2-2-5.jpg" server="cp23.g-dns.com/no70/" local="131438853031870492" remote="131441261400000000" />
<file name="75-2-2-6.jpg" server="cp23.g-dns.com/no70/" local="131438852890987602" remote="131441261400000000" />
<file name="75-2-2-7.jpg" server="cp23.g-dns.com/no70/" local="131438852722796244" remote="131441261400000000" />
<file name="75-2-2-8.jpg" server="cp23.g-dns.com/no70/" local="131438852504763558" remote="131441261400000000" />
<file name="75-2-2-1.jpg" server="cp23.g-dns.com/no71/" local="131495672639105585" remote="131495749800000000" />
<file name="75-2-2-2.jpg" server="cp23.g-dns.com/no71/" local="131495672797475695" remote="131495749800000000" />
<file name="75-2-2-3.jpg" server="cp23.g-dns.com/no71/" local="131495672941123936" remote="131495749800000000" />
<file name="75-2-2-4.jpg" server="cp23.g-dns.com/no71/" local="131495673700615379" remote="131495749800000000" />
<file name="75-2-2-5.jpg" server="cp23.g-dns.com/no71/" local="131495673874752492" remote="131495749800000000" />
<file name="75-2-2-6.jpg" server="cp23.g-dns.com/no71/" local="131495674086409369" remote="131495749800000000" />
<file name="75-2-2-7.jpg" server="cp23.g-dns.com/no71/" local="131495674286344757" remote="131495749800000000" />
<file name="75-2-2-8.jpg" server="cp23.g-dns.com/no71/" local="131495674445634985" remote="131495749800000000" />
<file name="75-2-2-1.jpg" server="cp23.g-dns.com/no72/" local="131546030184026542" remote="131546043000000000" />
<file name="75-2-2-2.jpg" server="cp23.g-dns.com/no72/" local="131546030026301514" remote="131546043000000000" />
<file name="75-2-2-3.jpg" server="cp23.g-dns.com/no72/" local="131546029836032353" remote="131546043000000000" />
<file name="75-2-2-4.jpg" server="cp23.g-dns.com/no72/" local="131546029672291560" remote="131546043000000000" />
<file name="75-2-2-5.jpg" server="cp23.g-dns.com/no72/" local="131546029175278447" remote="131546043000000000" />
<file name="75-2-2-6.jpg" server="cp23.g-dns.com/no72/" local="131546029006927070" remote="131546043000000000" />
<file name="75-2-2-7.jpg" server="cp23.g-dns.com/no72/" local="131546028087545323" remote="131546043000000000" />
<file name="75-2-2-8.jpg" server="cp23.g-dns.com/no72/" local="131546027918358839" remote="131546043000000000" />
<file name="75-2-2-1.jpg" server="cp23.g-dns.com/no73/" local="131653827943692190" remote="131653991400000000" />
<file name="75-2-2-2.jpg" server="cp23.g-dns.com/no73/" local="131653828209684860" remote="131653991400000000" />
<file name="75-2-2-3.jpg" server="cp23.g-dns.com/no73/" local="131653829291986318" remote="131653991400000000" />
<file name="75-2-2-4.jpg" server="cp23.g-dns.com/no73/" local="131653829090776602" remote="131653991400000000" />
<file name="75-2-2-5.jpg" server="cp23.g-dns.com/no73/" local="131653828912376920" remote="131653991400000000" />
<file name="75-2-2-6.jpg" server="cp23.g-dns.com/no73/" local="131653829801583665" remote="131653991400000000" />
<file name="75-2-2-7.jpg" server="cp23.g-dns.com/no73/" local="131653830093219936" remote="131653991400000000" />
<file name="75-2-2-8.jpg" server="cp23.g-dns.com/no73/" local="131653830312867006" remote="131653991400000000" />
<file name="75-2-2-1.jpg" server="cp23.g-dns.com/no75/" local="131759434753698736" remote="131759440200000000" />
<file name="75-2-2-2.jpg" server="cp23.g-dns.com/no75/" local="131759435023755886" remote="131759440200000000" />
<file name="75-2-2-3.jpg" server="cp23.g-dns.com/no75/" local="131759435285198272" remote="131759440200000000" />
<file name="75-2-2-4.jpg" server="cp23.g-dns.com/no75/" local="131759435505645146" remote="131759440200000000" />
<file name="75-2-2-5.jpg" server="cp23.g-dns.com/no75/" local="131759435708622035" remote="131759440200000000" />
<file name="75-2-2-6.jpg" server="cp23.g-dns.com/no75/" local="131759435922808918" remote="131759440200000000" />
<file name="75-2-2-7.jpg" server="cp23.g-dns.com/no75/" local="131759436177413933" remote="131759440200000000" />
<file name="75-2-2-8.jpg" server="cp23.g-dns.com/no75/" local="131759436347968884" remote="131759440200000000" />
<file name="75-2-2-1.jpg" server="cp23.g-dns.com/no75_chtest/" local="131759434753698736" remote="131798245200000000" />
<file name="75-2-2-2.jpg" server="cp23.g-dns.com/no75_chtest/" local="131759435023755886" remote="131798245200000000" />
<file name="75-2-2-3.jpg" server="cp23.g-dns.com/no75_chtest/" local="131759435285198272" remote="131798245200000000" />
<file name="75-2-2-4.jpg" server="cp23.g-dns.com/no75_chtest/" local="131759435505645146" remote="131798245200000000" />
<file name="75-2-2-5.jpg" server="cp23.g-dns.com/no75_chtest/" local="131759435708622035" remote="131798245200000000" />
<file name="75-2-2-6.jpg" server="cp23.g-dns.com/no75_chtest/" local="131759435922808918" remote="131798245200000000" />
<file name="75-2-2-7.jpg" server="cp23.g-dns.com/no75_chtest/" local="131759436177413933" remote="131798245200000000" />
<file name="75-2-2-8.jpg" server="cp23.g-dns.com/no75_chtest/" local="131759436347968884" remote="131798245200000000" />
<file name="75-2-2-1.jpg" server="cp23.g-dns.com/no78/" local="131967482549673418" remote="131967487800000000" />
<file name="75-2-2-2.jpg" server="cp23.g-dns.com/no78/" local="131967482397101145" remote="131967487800000000" />
<file name="75-2-2-3.jpg" server="cp23.g-dns.com/no78/" local="131967482221524074" remote="131967487800000000" />
<file name="75-2-2-4.jpg" server="cp23.g-dns.com/no78/" local="131967481673954037" remote="131967487800000000" />
<file name="75-2-2-5.jpg" server="cp23.g-dns.com/no78/" local="131967481524629744" remote="131967487800000000" />
<file name="75-2-2-6.jpg" server="cp23.g-dns.com/no78/" local="131967481329563582" remote="131967487800000000" />
<file name="75-2-2-7.jpg" server="cp23.g-dns.com/no78/" local="131967481176130508" remote="131967487800000000" />
<file name="75-2-2-8.jpg" server="cp23.g-dns.com/no78/" local="131967481029070278" remote="131967487800000000" />
<file name="75-2-2-1.jpg" server="cp23.g-dns.com/no79/" local="132018577038740886" remote="132018602400000000" />
<file name="75-2-2-2.jpg" server="cp23.g-dns.com/no79/" local="132018577539851118" remote="132018602400000000" />
<file name="75-2-2-3.jpg" server="cp23.g-dns.com/no79/" local="132018577348125087" remote="132018602400000000" />
<file name="75-2-2-4.jpg" server="cp23.g-dns.com/no79/" local="132018577712995780" remote="132018602400000000" />
<file name="75-2-2-5.jpg" server="cp23.g-dns.com/no79/" local="132018577880733268" remote="132018602400000000" />
<file name="75-2-2-6.jpg" server="cp23.g-dns.com/no79/" local="132018578019334854" remote="132018602400000000" />
<file name="75-2-2-7.jpg" server="cp23.g-dns.com/no79/" local="132018578158300288" remote="132018602400000000" />
<file name="75-2-2-8.jpg" server="cp23.g-dns.com/no79/" local="132018578372839342" remote="132018602400000000" />
<file name="75-2-2-9.jpg" server="cp23.g-dns.com/no79/" local="132018578552866156" remote="132018602400000000" />
<file name="75-2-2-1.jpg" server="cp23.g-dns.com/no80/" local="132071986559831910" remote="132072193800000000" />
<file name="75-2-2-2.jpg" server="cp23.g-dns.com/no80/" local="132071986395945863" remote="132072193800000000" />
<file name="75-2-2-3.jpg" server="cp23.g-dns.com/no80/" local="132071986206891243" remote="132072193800000000" />
<file name="75-2-2-4.jpg" server="cp23.g-dns.com/no80/" local="132071986045805888" remote="132072193800000000" />
<file name="75-2-2-5.jpg" server="cp23.g-dns.com/no80/" local="132071985824526354" remote="132072193800000000" />
<file name="75-2-2-6.jpg" server="cp23.g-dns.com/no80/" local="132071985528135170" remote="132072193800000000" />
<file name="75-2-2-7.jpg" server="cp23.g-dns.com/no80/" local="132071985337178080" remote="132072193800000000" />
<file name="75-2-2-8.jpg" server="cp23.g-dns.com/no80/" local="132071985073035253" remote="132072193800000000" />
<file name="75-2-2-9.jpg" server="cp23.g-dns.com/no80/" local="132071984817889151" remote="132072193800000000" />
<file name="75-2-2-10.jpg" server="cp23.g-dns.com/no80/" local="132071984626957402" remote="132072193800000000" />
<file name="75-2-2-1.jpg" server="cp23.g-dns.com/no81/" local="132124814958465780" remote="132131541000000000" />
<file name="75-2-2-2.jpg" server="cp23.g-dns.com/no81/" local="132124815202562821" remote="132131541000000000" />
<file name="75-2-2-3.jpg" server="cp23.g-dns.com/no81/" local="132124815425448909" remote="132131541000000000" />
<file name="75-2-2-4.jpg" server="cp23.g-dns.com/no81/" local="132124815646936186" remote="132131541000000000" />
<file name="75-2-2-5.jpg" server="cp23.g-dns.com/no81/" local="132124815894054421" remote="132131541000000000" />
<file name="75-2-2-6.jpg" server="cp23.g-dns.com/no81/" local="132124816692553309" remote="132131541000000000" />
<file name="75-2-2-7.jpg" server="cp23.g-dns.com/no81/" local="132124816869719997" remote="132131541000000000" />
<file name="75-2-2-8.jpg" server="cp23.g-dns.com/no81/" local="132124820918401572" remote="132131541000000000" />
<file name="75-2-2-9.jpg" server="cp23.g-dns.com/no81/" local="132124822259740576" remote="132131541000000000" />
<file name="75-2-2-10.jpg" server="cp23.g-dns.com/no81/" local="132124744342457357" remote="132131541000000000" />
<file name="75-2-2-1.jpg" server="cp23.g-dns.com/no82/" local="132174126131666439" remote="132174139200000000" />
<file name="75-2-2-2.jpg" server="cp23.g-dns.com/no82/" local="132174125962465109" remote="132174139800000000" />
<file name="75-2-2-3.jpg" server="cp23.g-dns.com/no82/" local="132174125807787111" remote="132174139800000000" />
<file name="75-2-2-4.jpg" server="cp23.g-dns.com/no82/" local="132174125652608952" remote="132174139800000000" />
<file name="75-2-2-5.jpg" server="cp23.g-dns.com/no82/" local="132174125497280565" remote="132174139800000000" />
<file name="75-2-2-6.jpg" server="cp23.g-dns.com/no82/" local="132174125318661858" remote="132174139800000000" />
<file name="75-2-2-7.jpg" server="cp23.g-dns.com/no82/" local="132174124823858574" remote="132174139800000000" />
<file name="75-2-2-8.jpg" server="cp23.g-dns.com/no82/" local="132174124669879984" remote="132174139800000000" />
<file name="75-2-2-9.jpg" server="cp23.g-dns.com/no82/" local="132174123998530508" remote="132174139800000000" />
<file name="75-2-2-10.jpg" server="cp23.g-dns.com/no82/" local="132174123746785476" remote="132174139200000000" />
<file name="75-2-2-1.jpg" server="cp23.g-dns.com/no83/" local="132282152608777703" remote="132282152400000000" />
<file name="75-2-2-2.jpg" server="cp23.g-dns.com/no83/" local="132282152395711158" remote="132282152400000000" />
<file name="75-2-2-3.jpg" server="cp23.g-dns.com/no83/" local="132282152130701014" remote="132282152400000000" />
<file name="75-2-2-4.jpg" server="cp23.g-dns.com/no83/" local="132282151938392079" remote="132282152400000000" />
<file name="75-2-2-5.jpg" server="cp23.g-dns.com/no83/" local="132282151678108354" remote="132282152400000000" />
<file name="75-2-2-6.jpg" server="cp23.g-dns.com/no83/" local="132282151249285735" remote="132282152400000000" />
<file name="75-2-2-7.jpg" server="cp23.g-dns.com/no83/" local="132282151027336841" remote="132282152400000000" />
<file name="75-2-2-8.jpg" server="cp23.g-dns.com/no83/" local="132282150767563549" remote="132282152400000000" />
<file name="75-2-2-9.jpg" server="cp23.g-dns.com/no83/" local="132282150595130542" remote="132282152400000000" />
<file name="75-2-2-10.jpg" server="cp23.g-dns.com/no83/" local="132282149621626951" remote="132282152400000000" />
<file name="75-2-2-1.jpg" server="cp23.g-dns.com/no84/" local="132333903281346032" remote="132333903600000000" />
<file name="75-2-2-2.jpg" server="cp23.g-dns.com/no84/" local="132333903114365894" remote="132333903600000000" />
<file name="75-2-2-3.jpg" server="cp23.g-dns.com/no84/" local="132333902887676878" remote="132333903600000000" />
<file name="75-2-2-4.jpg" server="cp23.g-dns.com/no84/" local="132333902567935065" remote="132333903600000000" />
<file name="75-2-2-5.jpg" server="cp23.g-dns.com/no84/" local="132333902382628834" remote="132333903600000000" />
<file name="75-2-2-6.jpg" server="cp23.g-dns.com/no84/" local="132333902191753320" remote="132333903600000000" />
<file name="75-2-2-7.jpg" server="cp23.g-dns.com/no84/" local="132333901997814492" remote="132333903600000000" />
<file name="75-2-2-8.jpg" server="cp23.g-dns.com/no84/" local="132333901812265351" remote="132333903600000000" />
<file name="75-2-2-9.jpg" server="cp23.g-dns.com/no84/" local="132333901635825697" remote="132333903600000000" />
<file name="75-2-2-10.jpg" server="cp23.g-dns.com/no84/" local="132333901452722746" remote="132333903600000000" />
<file name="75-2-2-1.psd" server="cp23.g-dns.com/no84/" local="132333904002551701" remote="132333903600000000" />
<file name="75-2-2-11.jpg" server="cp23.g-dns.com/no84/" local="132333901235613768" remote="132333903600000000" />
<file name="75-2-2-1.jpg" server="cp23.g-dns.com/no85/" local="132382377702094711" remote="132392706000000000" />
<file name="75-2-2-2.jpg" server="cp23.g-dns.com/no85/" local="132382378356871061" remote="132392706000000000" />
<file name="75-2-2-3.jpg" server="cp23.g-dns.com/no85/" local="132382378584938779" remote="132392706000000000" />
<file name="75-2-2-4.jpg" server="cp23.g-dns.com/no85/" local="132382378876940121" remote="132392706000000000" />
<file name="75-2-2-5.jpg" server="cp23.g-dns.com/no85/" local="132382379081704559" remote="132392706000000000" />
<file name="75-2-2-6.jpg" server="cp23.g-dns.com/no85/" local="132382379297718362" remote="132392706000000000" />
<file name="75-2-2-7.jpg" server="cp23.g-dns.com/no85/" local="132382379542135946" remote="132392706000000000" />
<file name="75-2-2-8.jpg" server="cp23.g-dns.com/no85/" local="132382379811792044" remote="132392706000000000" />
<file name="75-2-2-9.jpg" server="cp23.g-dns.com/no85/" local="132382380069045656" remote="132392706000000000" />
<file name="75-2-2-10.jpg" server="cp23.g-dns.com/no85/" local="132382380289988153" remote="132392706000000000" />
<file name="75-2-2-11.jpg" server="cp23.g-dns.com/no85/" local="132382380500006051" remote="132392706000000000" />
<file name="75-2-2-12.jpg" server="cp23.g-dns.com/no85/" local="132382380788907364" remote="132392706000000000" />
<file name="75-2-2-13.jpg" server="cp23.g-dns.com/no85/" local="132382381000107181" remote="132392706000000000" />
<file name="75-2-2-14.jpg" server="cp23.g-dns.com/no85/" local="132382381298632374" remote="132392706000000000" />
<file name="75-2-2-15.jpg" server="cp23.g-dns.com/no85/" local="132382381581680278" remote="132392706000000000" />
<file name="75-2-2-16.jpg" server="cp23.g-dns.com/no85/" local="132382381851464693" remote="132392706000000000" />
<file name="75-2-2-17.jpg" server="cp23.g-dns.com/no85/" local="132382382187917055" remote="132392706000000000" />
<file name="75-2-2-18.jpg" server="cp23.g-dns.com/no85/" local="132382382447112701" remote="132392706000000000" />
<file name="75-2-2-19.jpg" server="cp23.g-dns.com/no85/" local="132382382715347705" remote="132392706000000000" />
<file name="75-2-2-20.jpg" server="cp23.g-dns.com/no85/" local="132382382978348108" remote="132392706000000000" />
<file name="75-2-2-21.jpg" server="cp23.g-dns.com/no85/" local="132382383208875486" remote="132392706000000000" />
<file name="75-2-2-22.jpg" server="cp23.g-dns.com/no85/" local="132382383439470898" remote="132392706000000000" />
<file name="75-2-2-23.jpg" server="cp23.g-dns.com/no85/" local="132382383687909853" remote="132392706000000000" />
<file name="75-2-2-24.jpg" server="cp23.g-dns.com/no85/" local="132382384078129593" remote="132392706000000000" />
<file name="75-2-2-25.jpg" server="cp23.g-dns.com/no85/" local="132382384320599036" remote="132392706000000000" />
<file name="75-2-2-26.jpg" server="cp23.g-dns.com/no85/" local="132382384555544744" remote="132392706000000000" />
<file name="75-2-2-27.jpg" server="cp23.g-dns.com/no85/" local="132382384830680608" remote="132392706000000000" />
<file name="75-2-2-28.jpg" server="cp23.g-dns.com/no85/" local="132382385147485955" remote="132392706000000000" />
<file name="75-2-2-29.jpg" server="cp23.g-dns.com/no85/" local="132382385462618400" remote="132392706000000000" />
<file name="75-2-2-30.jpg" server="cp23.g-dns.com/no85/" local="132382385750817379" remote="132392706000000000" />
<file name="75-2-2-1.psd" server="cp23.g-dns.com/no85/" local="132384744552180496" remote="132392706000000000" />
<file name="75-2-2-31.jpg" server="cp23.g-dns.com/no85/" local="132384744771395250" remote="132392706000000000" />
<file name="75-2-2-1.jpg" server="cp23.g-dns.com/no86/" local="132441080488559053" remote="132441088200000000" />
<file name="75-2-2-2.jpg" server="cp23.g-dns.com/no86/" local="132441080695072049" remote="132441088200000000" />
<file name="75-2-2-3.jpg" server="cp23.g-dns.com/no86/" local="132441080883318051" remote="132441088200000000" />
<file name="75-2-2-4.jpg" server="cp23.g-dns.com/no86/" local="132441081068429559" remote="132441088200000000" />
<file name="75-2-2-5.jpg" server="cp23.g-dns.com/no86/" local="132441081237690762" remote="132441088200000000" />
<file name="75-2-2-6.jpg" server="cp23.g-dns.com/no86/" local="132441082078761256" remote="132441088200000000" />
<file name="75-2-2-7.jpg" server="cp23.g-dns.com/no86/" local="132441081905413343" remote="132441088200000000" />
<file name="75-2-2-8.jpg" server="cp23.g-dns.com/no86/" local="132441082385193681" remote="132441088200000000" />
<file name="75-2-2-9.jpg" server="cp23.g-dns.com/no86/" local="132441082554978509" remote="132441088200000000" />
<file name="75-2-2-10.jpg" server="cp23.g-dns.com/no86/" local="132441082741036073" remote="132441088200000000" />
<file name="75-2-2-11.jpg" server="cp23.g-dns.com/no86/" local="132441082968417141" remote="132441088200000000" />
<file name="75-2-2-12.jpg" server="cp23.g-dns.com/no86/" local="132441083200265002" remote="132441088200000000" />
<file name="75-2-2-13.jpg" server="cp23.g-dns.com/no86/" local="132441083485535626" remote="132441088200000000" />
<file name="75-2-2-14.jpg" server="cp23.g-dns.com/no86/" local="132441083711053071" remote="132441088200000000" />
<file name="75-2-2-15.jpg" server="cp23.g-dns.com/no86/" local="132441083896764186" remote="132441088200000000" />
<file name="75-2-2-16.jpg" server="cp23.g-dns.com/no86/" local="132441084088326041" remote="132441088200000000" />
<file name="75-2-2-17.jpg" server="cp23.g-dns.com/no86/" local="132441084296543940" remote="132441088200000000" />
<file name="75-2-2-18.jpg" server="cp23.g-dns.com/no86/" local="132441084500950449" remote="132441088200000000" />
<file name="75-2-2-19.jpg" server="cp23.g-dns.com/no86/" local="132441085402137161" remote="132441088200000000" />
<file name="75-2-2-20.jpg" server="cp23.g-dns.com/no86/" local="132441085568364447" remote="132441088200000000" />
<file name="75-2-2-21.jpg" server="cp23.g-dns.com/no86/" local="132441085766445801" remote="132441088200000000" />
<file name="75-2-2-22.jpg" server="cp23.g-dns.com/no86/" local="132441085964661584" remote="132441088200000000" />
<file name="75-2-2-23.jpg" server="cp23.g-dns.com/no86/" local="132441086212671483" remote="132441088200000000" />
<file name="75-2-2-24.jpg" server="cp23.g-dns.com/no86/" local="132441086804615802" remote="132441088200000000" />
<file name="75-2-2-25.jpg" server="cp23.g-dns.com/no86/" local="132441087002236336" remote="132441088200000000" />
<file name="75-2-2-26.jpg" server="cp23.g-dns.com/no86/" local="132441087200491722" remote="132441088200000000" />
<file name="75-2-2-27.jpg" server="cp23.g-dns.com/no86/" local="132441087353587324" remote="132441088200000000" />
<file name="75-2-2-28.jpg" server="cp23.g-dns.com/no86/" local="132441087535933579" remote="132441088200000000" />
<file name="75-2-2-29.jpg" server="cp23.g-dns.com/no86/" local="132441087694723886" remote="132441088200000000" />
<file name="75-2-2-30.jpg" server="cp23.g-dns.com/no86/" local="132441087854437154" remote="132441088200000000" />
<file name="75-2-2-31.jpg" server="cp23.g-dns.com/no86/" local="132441088091529721" remote="132441088200000000" />
<file name="75-2-2-1.psd" server="cp23.g-dns.com/no86/" local="132441088151787522" remote="132441088200000000" />
</dwsync>